__init__.py
gdata_vaas-6.0.4.dist-info/licenses/LICENSE
vaas/__init__.py
vaas/async_file_reader.py
vaas/sha256.py
vaas/vaas.py
vaas/vaas_errors.py
vaas/authentication/__init__.py
vaas/authentication/authenticator_interface.py
vaas/authentication/client_credentials_grant_authenticator.py
vaas/authentication/resource_owner_password_grant_authenticator.py
vaas/messages/file_analysis_started.py
vaas/messages/file_report.py
vaas/messages/problem_details.py
vaas/messages/url_analysis_request.py
vaas/messages/url_analysis_started.py
vaas/messages/url_report.py
vaas/messages/vaas_verdict.py
vaas/options/for_file_options.py
vaas/options/for_sha256_options.py
vaas/options/for_stream_options.py
vaas/options/for_url_options.py
gdata_vaas-6.0.4.dist-info/METADATA
gdata_vaas-6.0.4.dist-info/WHEEL
gdata_vaas-6.0.4.dist-info/top_level.txt
gdata_vaas-6.0.4.dist-info/RECORD
