Metadata-Version: 2.4
Name: gdata-vaas
Version: 6.0.4
Summary: G DATA Verdict-as-a-Service Python client
Requires-Python: >=3.10
License-File: LICENSE
Requires-Dist: authlib>=1.6.6
Requires-Dist: python-dotenv>=1.2.1
Requires-Dist: httpx[http2]>=0.28.1
Requires-Dist: aiofiles<26,>=24.1
Requires-Dist: pydantic<3,>=2.12
Provides-Extra: test
Requires-Dist: pytest>=9.0.2; extra == "test"
Requires-Dist: pytest-asyncio>=1.3.0; extra == "test"
Requires-Dist: pytest-httpx>=0.36.0; extra == "test"
Provides-Extra: build
Requires-Dist: build>=1.4.0; extra == "build"
Provides-Extra: dev
Requires-Dist: build>=1.4.0; extra == "dev"
Requires-Dist: pytest>=9.0.2; extra == "dev"
Requires-Dist: pytest-asyncio>=1.3.0; extra == "dev"
Requires-Dist: pytest-httpx>=0.36.0; extra == "dev"
Dynamic: license-file
